x01replace/__init__.py
x01replace/script.py
x01replace-1.0.1.dist-info/METADATA
x01replace-1.0.1.dist-info/WHEEL
x01replace-1.0.1.dist-info/entry_points.txt
x01replace-1.0.1.dist-info/top_level.txt
x01replace-1.0.1.dist-info/RECORD
