Metadata-Version: 2.1
Name: x01replace
Version: 1.0.1
Summary: A tool to replace \x01 with |
Author: tangjicheng
Author-email: tangjch15@gmail.com
Classifier: Programming Language :: Python :: 3
Classifier: License :: OSI Approved :: MIT License
Classifier: Operating System :: OS Independent
